vectorpython/__about__.py
vectorpython/__init__.py
vectorpython/main.py
vectorpython/vector_operations.py
vectorpython-0.0.1.dist-info/METADATA
vectorpython-0.0.1.dist-info/WHEEL
vectorpython-0.0.1.dist-info/entry_points.txt
vectorpython-0.0.1.dist-info/licenses/LICENSE.txt
vectorpython-0.0.1.dist-info/RECORD
