Metadata-Version: 2.3
Name: VectorPython
Version: 0.0.1
Project-URL: Documentation, https://github.com/kharvey2/vectorpython#readme
Project-URL: Issues, https://github.com/kharvey2/vectorpython/issues
Project-URL: Source, https://github.com/kharvey2/vectorpython
Author-email: kharvey2 <kharvey@nvidia.com>
License-Expression: MIT
License-File: LICENSE.txt
Classifier: Development Status :: 4 - Beta
Classifier: Programming Language :: Python
Classifier: Programming Language :: Python :: 3.8
Classifier: Programming Language :: Python :: 3.9
Classifier: Programming Language :: Python :: 3.10
Classifier: Programming Language :: Python :: 3.11
Classifier: Programming Language :: Python :: 3.12
Classifier: Programming Language :: Python :: Implementation :: CPython
Classifier: Programming Language :: Python :: Implementation :: PyPy
Requires-Python: >=3.8
